database_setup_tools/__init__.py
database_setup_tools/session_manager.py
database_setup_tools/setup.py
database_setup_tools-1.3.1.dist-info/LICENSE
database_setup_tools-1.3.1.dist-info/METADATA
database_setup_tools-1.3.1.dist-info/WHEEL
database_setup_tools-1.3.1.dist-info/RECORD
