Metadata-Version: 2.1
Name: database-setup-tools
Version: 1.3.1
Summary: Tools to easily setup databases opinionated towards FastAPI and SQLModel
License: MIT
Author: Jonas Scholl
Author-email: jonas@code-specialist.com
Requires-Python: >=3.9,<4.0
Classifier: License :: OSI Approved :: MIT License
Classifier: Programming Language :: Python :: 3
Classifier: Programming Language :: Python :: 3.9
Classifier: Programming Language :: Python :: 3.10
Classifier: Programming Language :: Python :: 3.11
Requires-Dist: sqlalchemy (>=1.4.41,<2.0.0)
Requires-Dist: sqlalchemy-utils (>=0.38.3,<0.41.0)
